<?xml version="1.0" ?><Level title="$LEVEL_BLOCKS_39" skin0="blocks_03" skin1="blocks_03" skin2="" skin3="blocks_03" skin4="" skin5="" skin6="" skin7="" skin8="" skin9="" skin10="" width="40" height="25" numLayers="2" numDiamondsNeeded="2" electricityOn="1" nightVision="1" raining="0" clouds="0" snowing="0" thunderstorm="0" lightColorR="255" lightColorG="255" lightColorB="255" musicFilename="music5.ogg"><Layer><Row>.................44444..................</Row><Row>................34a7b4...........44.5...</Row><Row>................345.34...........4445...</Row><Row>................34c1d4...........44.5...</Row><Row>..0111111111111234.44...........44ca801.</Row><Row>..3444444444444567777..........644480d4.</Row><Row>..3a7777777777bc112.............fff.344.</Row><Row>..35..........677bc2............ggg.344.</Row><Row>..35.............6b5............ggg.344.</Row><Row>..35..............35............ggg.344.</Row><Row>..35..............35............ggg.344.</Row><Row>..35..............35............ggg.344.</Row><Row>..35..............35............ggg.344.</Row><Row>..35..............35............ggg.344.</Row><Row>..35..............35............ggg.344.</Row><Row>..35..............35............ggg.6b4.</Row><Row>..35..............35...........04442.67.</Row><Row>..35..............35..........0d444c2...</Row><Row>..35..............35..........3444445...</Row><Row>..3c11111111111111d5..........3444445...</Row><Row>..677777777777777778..........6777778...</Row><Row>........................................</Row><Row>........................................</Row><Row>.44444444444444444444...................</Row><Row>........................................</Row></Layer><Layer><Row>AMMMMMMMMMMMMMMMMMMMMMmmmMMMMAUSSiSWAMMA</Row><Row>M                    MmEmMKKKKUSW ZW   M</Row><Row>M                M   MmmmMJJJJUSW  W   M</Row><Row>M                M   MmEmM    UDW PW   M</Row><Row>M                AMM MmmmM    Zij Zj   M</Row><Row>M                    MMMMA             M</Row><Row>M                    AM    PQQR       PQ</Row><Row>M                       MA USIW      PSS</Row><Row>M                    AMMMM USSW      UiS</Row><Row>M                    MmmmM UjZW      U U</Row><Row>M         AEA    AMMMMmEmM URPW      U U</Row><Row>M         M M        MmmmM USSW      U U</Row><Row>MM  MMMMMMM MMMMMMMMMMmEmM UHSj      UQS</Row><Row>Mm  mmmmmmM MmmmmmmmmMmmmM USj       ZSS</Row><Row>Mm  mmmmmmA AmmmmmmmmMmmmM Zj         Zi</Row><Row>M                    MmmmM             M</Row><Row>M                    MmDmM      PQR    M</Row><Row>M                    MmmmM     PSSW    M</Row><Row>M                    MmmmM     USDW    M</Row><Row>M                    MmmmM     Ziij    M</Row><Row>M                    MmmmM             M</Row><Row>M                    MmDmM          AM M</Row><Row>AMMMMMMMMMMMMMMMMMMMMAmmmM          M  M</Row><Row>M                    MmmmM             M</Row><Row>AMMMMMMMMMMMMMMMMMMMMAmmmAMMMMMMMMMMMMMA</Row></Layer><Object type="Barrage2Panel" x="34" y="2" subType="1" color="0" /><Object type="Barrage2Panel" x="24" y="6" subType="1" color="1" /><Object type="ElectricityPanel" x="22" y="7" subType="1" /><Object type="LightPanel" x="38" y="23" subType="1" /><Object type="Lava" x="30" y="2" dir="1" /><Object type="Lava" x="26" y="2" dir="1" /><Object type="Lava" x="29" y="2" dir="1" /><Object type="Lava" x="25" y="2" dir="1" /><Object type="Lava" x="28" y="2" dir="1" /><Object type="Lava" x="27" y="2" dir="1" /><Object type="Lava" x="26" y="3" dir="1" /><Object type="Lava" x="30" y="3" dir="1" /><Object type="Lava" x="25" y="3" dir="1" /><Object type="Lava" x="28" y="3" dir="1" /><Object type="Lava" x="29" y="3" dir="1" /><Object type="Lava" x="27" y="3" dir="1" /><Object type="Lava" x="29" y="9" dir="9" /><Object type="Lava" x="28" y="9" dir="8" /><Object type="Lava" x="28" y="10" dir="11" /><Object type="Lava" x="29" y="10" dir="10" /><Object type="Lava" x="32" y="17" dir="1" /><Object type="Lava" x="27" y="17" dir="8" /><Object type="Lava" x="29" y="17" dir="1" /><Object type="Lava" x="31" y="17" dir="1" /><Object type="Lava" x="30" y="17" dir="1" /><Object type="Lava" x="28" y="17" dir="1" /><Object type="Lava" x="28" y="18" dir="8" /><Object type="Lava" x="30" y="18" dir="1" /><Object type="Lava" x="27" y="18" dir="0" /><Object type="Lava" x="31" y="18" dir="1" /><Object type="Lava" x="29" y="18" dir="1" /><Object type="Lava" x="28" y="19" dir="0" /><Object type="Lava" x="27" y="19" dir="0" /><Object type="Lava" x="27" y="20" dir="0" /><Object type="Lava" x="28" y="20" dir="0" /><Object type="Lava" x="28" y="21" dir="0" /><Object type="Lava" x="27" y="21" dir="0" /><Object type="Lava" x="28" y="22" dir="0" /><Object type="Lava" x="27" y="22" dir="0" /><Object type="Lava" x="28" y="23" dir="0" /><Object type="Lava" x="27" y="23" dir="0" /><Object type="Lava" x="27" y="24" dir="0" /><Object type="Lava" x="28" y="24" dir="0" /><Object type="E_Barrage" x="17" y="11" dir="0"><OutputConnections /></Object><Object type="E_Barrage" x="11" y="12" dir="0"><OutputConnections /></Object><Object type="Rail" x="33" y="2" subType="0" dir="0" /><Object type="Rail" x="33" y="3" subType="0" dir="0" /><Object type="Rail" x="33" y="4" subType="0" dir="0" /><Object type="Rail" x="33" y="5" subType="0" dir="0" /><Object type="Rail" x="33" y="6" subType="0" dir="0" /><Object type="Rail" x="33" y="7" subType="0" dir="0" /><Object type="Rail" x="33" y="8" subType="0" dir="0" /><Object type="Rail" x="33" y="9" subType="0" dir="0" /><Object type="Rail" x="33" y="10" subType="0" dir="0" /><Object type="Rail" x="33" y="11" subType="0" dir="0" /><Object type="Rail" x="33" y="12" subType="0" dir="0" /><Object type="Rail" x="33" y="13" subType="0" dir="0" /><Object type="Rail" x="33" y="14" subType="0" dir="0" /><Object type="Rail" x="33" y="15" subType="0" dir="0" /><Object type="Elevator" x="33" y="13" dir="0" /><Object type="Elevator" x="33" y="14" dir="0" /><Object type="Arrow" x="17" y="1" dir="3" /><Object type="Arrow" x="20" y="4" dir="0" /><Object type="Exit" x="1" y="11" /><Object type="Arrow" x="3" y="12" dir="0" /><Object type="Arrow" x="2" y="12" dir="2" /><Object type="Arrow" x="3" y="13" dir="0" /><Object type="Arrow" x="2" y="13" dir="2" /><Object type="Arrow" x="2" y="14" dir="2" /><Object type="Arrow" x="3" y="14" dir="0" /><Object type="Arrow" x="38" y="21" dir="0" /><Object type="Arrow" x="36" y="23" dir="1" /><Object type="Hint" x="38" y="5"><Text><![CDATA[$HINT_BLOCKS_39_01]]></Text></Object><Object type="Hint" x="19" y="6"><Text><![CDATA[$HINT_BLOCKS_39_02]]></Text></Object><Object type="E_LightBulb" x="15" y="1" dir="0"><OutputConnections /></Object><Object type="E_LightBulb" x="13" y="1" dir="0"><OutputConnections /></Object><Object type="Laser" x="33" y="1" dir="2" /><Object type="E_LightBulb" x="2" y="1" dir="0"><OutputConnections /></Object><Object type="E_LightBulb" x="10" y="1" dir="0"><OutputConnections /></Object><Object type="E_LightBulb" x="6" y="1" dir="0"><OutputConnections /></Object><Object type="Hotel" x="19" y="2" /><Object type="Bomb" x="34" y="2" /><Object type="E_Gate" x="13" y="3" dir="3" subType="6"><OutputConnections><Connection sourcePinID="10" targetX="13" targetY="1" targetPinID="0" /></OutputConnections></Object><Object type="E_Gate" x="10" y="3" dir="3" subType="0"><OutputConnections><Connection sourcePinID="10" targetX="10" targetY="1" targetPinID="0" /></OutputConnections></Object><Object type="E_Gate" x="6" y="3" dir="3" subType="2"><OutputConnections><Connection sourcePinID="10" targetX="6" targetY="1" targetPinID="0" /></OutputConnections></Object><Object type="E_Gate" x="2" y="3" dir="3" subType="4"><OutputConnections><Connection sourcePinID="10" targetX="2" targetY="1" targetPinID="0" /></OutputConnections></Object><Object type="Barrage2" x="28" y="4" up="1" color="0" /><Object type="E_ValueSwitch" x="13" y="5" dir="2" value="0"><OutputConnections><Connection sourcePinID="10" targetX="13" targetY="3" targetPinID="0" /></OutputConnections></Object><Object type="E_ValueSwitch" x="15" y="5" dir="2" value="0"><OutputConnections><Connection sourcePinID="10" targetX="15" targetY="1" targetPinID="0" /></OutputConnections></Object><Object type="E_ValueSwitch" x="5" y="5" dir="2" value="0"><OutputConnections><Connection sourcePinID="10" targetX="6" targetY="3" targetPinID="0" /></OutputConnections></Object><Object type="E_ValueSwitch" x="7" y="5" dir="2" value="0"><OutputConnections><Connection sourcePinID="10" targetX="6" targetY="3" targetPinID="1" /></OutputConnections></Object><Object type="E_ValueSwitch" x="9" y="5" dir="2" value="0"><OutputConnections><Connection sourcePinID="10" targetX="10" targetY="3" targetPinID="0" /></OutputConnections></Object><Object type="E_ValueSwitch" x="11" y="5" dir="2" value="0"><OutputConnections><Connection sourcePinID="10" targetX="10" targetY="3" targetPinID="1" /></OutputConnections></Object><Object type="Barrage2" x="28" y="5" up="1" color="0" /><Object type="E_ValueSwitch" x="1" y="5" dir="2" value="0"><OutputConnections><Connection sourcePinID="10" targetX="2" targetY="3" targetPinID="0" /></OutputConnections></Object><Object type="E_ValueSwitch" x="3" y="5" dir="2" value="0"><OutputConnections><Connection sourcePinID="10" targetX="2" targetY="3" targetPinID="1" /></OutputConnections></Object><Object type="Barrage" x="25" y="6" up="1" color="0" /><Object type="Barrage" x="21" y="7" up="1" color="0" /><Object type="E_ValueSwitch" x="8" y="8" dir="0" value="0"><OutputConnections><Connection sourcePinID="10" targetX="8" targetY="10" targetPinID="0" /></OutputConnections></Object><Object type="E_ValueSwitch" x="5" y="8" dir="0" value="0"><OutputConnections><Connection sourcePinID="10" targetX="8" targetY="10" targetPinID="3" /></OutputConnections></Object><Object type="E_ValueSwitch" x="6" y="8" dir="0" value="0"><OutputConnections><Connection sourcePinID="10" targetX="8" targetY="10" targetPinID="2" /></OutputConnections></Object><Object type="E_ValueSwitch" x="7" y="8" dir="0" value="0"><OutputConnections><Connection sourcePinID="10" targetX="8" targetY="10" targetPinID="1" /></OutputConnections></Object><Object type="Barrage2" x="31" y="8" up="1" color="0" /><Object type="ActivatorBlock" x="38" y="9" shielded="0" /><Object type="E_HexDigit" x="8" y="10" dir="0"><OutputConnections /></Object><Object type="Barrage2" x="38" y="10" up="1" color="1" /><Object type="E_ValueSwitch" x="15" y="11" dir="3" value="1"><OutputConnections><Connection sourcePinID="10" targetX="17" targetY="11" targetPinID="0" /></OutputConnections></Object><Object type="Diamond" x="20" y="11" /><Object type="Diamond" x="11" y="11" /><Object type="BarrageSwitch" x="38" y="11" color="0" /><Object type="E_LightBulb" x="20" y="15" dir="0"><OutputConnections /></Object><Object type="E_PulseSwitch" x="16" y="15" dir="3" pulseValue="1"><OutputConnections><Connection sourcePinID="10" targetX="18" targetY="16" targetPinID="0" /></OutputConnections></Object><Object type="E_LightBulb" x="7" y="15" dir="0"><OutputConnections /></Object><Object type="E_LightBulb" x="5" y="15" dir="0"><OutputConnections /></Object><Object type="E_FlipFlop" x="18" y="16" dir="0" subType="0" value="0"><OutputConnections><Connection sourcePinID="10" targetX="20" targetY="15" targetPinID="0" /></OutputConnections></Object><Object type="E_Gate" x="11" y="16" dir="3" subType="6"><OutputConnections><Connection sourcePinID="10" targetX="11" targetY="12" targetPinID="0" /></OutputConnections></Object><Object type="E_PulseSwitch" x="16" y="17" dir="3" pulseValue="1"><OutputConnections><Connection sourcePinID="10" targetX="18" targetY="16" targetPinID="1" /></OutputConnections></Object><Object type="E_PulsePanel" x="5" y="17" dir="2" pulseValue="1"><OutputConnections><Connection sourcePinID="10" targetX="5" targetY="15" targetPinID="0" /></OutputConnections></Object><Object type="E_PulsePanel" x="7" y="17" dir="2" pulseValue="0"><OutputConnections><Connection sourcePinID="10" targetX="7" targetY="15" targetPinID="0" /></OutputConnections></Object><Object type="E_Gate" x="13" y="18" dir="3" subType="4"><OutputConnections><Connection sourcePinID="10" targetX="11" targetY="18" targetPinID="1" /></OutputConnections></Object><Object type="E_Gate" x="9" y="18" dir="3" subType="0"><OutputConnections><Connection sourcePinID="10" targetX="11" targetY="18" targetPinID="0" /></OutputConnections></Object><Object type="E_Gate" x="11" y="18" dir="3" subType="0"><OutputConnections><Connection sourcePinID="10" targetX="11" targetY="16" targetPinID="0" /></OutputConnections></Object><Object type="E_LightBulb" x="20" y="19" dir="0"><OutputConnections /></Object><Object type="E_LightBulb" x="1" y="19" dir="2"><OutputConnections /></Object><Object type="E_Clock" x="16" y="19" dir="0"><OutputConnections><Connection sourcePinID="10" targetX="18" targetY="20" targetPinID="0" /></OutputConnections></Object><Object type="E_PulseSwitch" x="3" y="19" dir="2" pulseValue="1"><OutputConnections><Connection sourcePinID="10" targetX="1" targetY="19" targetPinID="0" /></OutputConnections></Object><Object type="Bomb" x="29" y="19" /><Object type="E_Gate" x="18" y="20" dir="0" subType="0"><OutputConnections><Connection sourcePinID="10" targetX="20" targetY="19" targetPinID="0" /></OutputConnections></Object><Object type="E_ValueSwitch" x="8" y="20" dir="2" value="0"><OutputConnections><Connection sourcePinID="10" targetX="9" targetY="18" targetPinID="0" /></OutputConnections></Object><Object type="E_ValueSwitch" x="10" y="20" dir="2" value="0"><OutputConnections><Connection sourcePinID="10" targetX="9" targetY="18" targetPinID="1" /></OutputConnections></Object><Object type="E_ValueSwitch" x="12" y="20" dir="2" value="0"><OutputConnections><Connection sourcePinID="10" targetX="13" targetY="18" targetPinID="0" /></OutputConnections></Object><Object type="E_ValueSwitch" x="14" y="20" dir="2" value="0"><OutputConnections><Connection sourcePinID="10" targetX="13" targetY="18" targetPinID="1" /></OutputConnections></Object><Object type="Box" x="33" y="20" /><Object type="E_PulseSwitch" x="3" y="21" dir="2" pulseValue="0"><OutputConnections><Connection sourcePinID="10" targetX="1" targetY="21" targetPinID="0" /></OutputConnections></Object><Object type="E_LightBulb" x="1" y="21" dir="2"><OutputConnections /></Object><Object type="E_ValueSwitch" x="16" y="21" dir="3" value="1"><OutputConnections><Connection sourcePinID="10" targetX="18" targetY="20" targetPinID="1" /></OutputConnections></Object><Object type="Barrage" x="20" y="23" up="1" color="0" /><Object type="Barrage" x="1" y="23" up="1" color="0" /><Object type="BarrageSwitch" x="26" y="23" color="0" /><Object type="Player" x="37" y="2" character="0" active="1" /><Object type="Enemy" x="19" y="11" subType="1" dir="0" /><Object type="Enemy" x="11" y="23" subType="0" dir="1" /></Level>